audioextractor/__init__.py
audioextractor/extractor.py
audioextractor-0.0.3.dist-info/LICENSE
audioextractor-0.0.3.dist-info/METADATA
audioextractor-0.0.3.dist-info/WHEEL
audioextractor-0.0.3.dist-info/top_level.txt
audioextractor-0.0.3.dist-info/RECORD
